pyhera/__init__.py
pyhera-0.5.3.dist-info/LICENSE
pyhera-0.5.3.dist-info/METADATA
pyhera-0.5.3.dist-info/WHEEL
pyhera-0.5.3.dist-info/top_level.txt
pyhera-0.5.3.dist-info/RECORD
