Metadata-Version: 2.1
Name: pyhera
Version: 0.5.3
Summary: pyhera is an optimized in-memory database
Home-page: https://github.com/lstil/pyhera
Author: Ali Moghimi
Author-email: thisisjavid@gmail.com
License: MIT
Keywords: dbms,database,nosql,pyhera db,hera,pyhera,pyhera database
Platform: UNKNOWN
Classifier: Development Status :: 4 - Beta
Classifier: Intended Audience :: Developers
Classifier: Topic :: Software Development :: Build Tools
Classifier: License :: OSI Approved :: MIT License
